LICENSE
README.md
pyproject.toml
./coco/__init__.py
./coco/cm3toppm.py
./coco/decb_to_b09.py
./coco/hrstoppm.py
./coco/maxtoppm.py
./coco/mge_viewer2.py
./coco/mgetoppm.py
./coco/pixtopgm.py
./coco/rattoppm.py
./coco/util.py
./coco/veftopng.py
./coco/b09/__init__.py
./coco/b09/compiler.py
./coco/b09/configs.py
./coco/b09/elements.py
./coco/b09/error_handler.py
./coco/b09/grammar.py
./coco/b09/parser.py
./coco/b09/procbank.py
./coco/b09/prog.py
./coco/b09/visitors.py
./coco/resources/__init__.py
./coco/resources/ecb.b09
./tests/test_error_handler.py
./tests/coco_tests/b09/__init__.py
./tests/coco_tests/b09/test_b09.py
./tests/coco_tests/b09/test_configs.py
./tests/coco_tests/b09/test_visitors.py
./tests/coco_tests/fixtures/__init__.py
coco/__init__.py
coco/cm3toppm.py
coco/decb_to_b09.py
coco/hrstoppm.py
coco/maxtoppm.py
coco/mge_viewer2.py
coco/mgetoppm.py
coco/pixtopgm.py
coco/rattoppm.py
coco/util.py
coco/veftopng.py
coco/b09/__init__.py
coco/b09/compiler.py
coco/b09/configs.py
coco/b09/elements.py
coco/b09/error_handler.py
coco/b09/grammar.py
coco/b09/parser.py
coco/b09/procbank.py
coco/b09/prog.py
coco/b09/visitors.py
coco/resources/__init__.py
coco/resources/ecb.b09
coco_tools.egg-info/PKG-INFO
coco_tools.egg-info/SOURCES.txt
coco_tools.egg-info/dependency_links.txt
coco_tools.egg-info/entry_points.txt
coco_tools.egg-info/requires.txt
coco_tools.egg-info/top_level.txt
tests/test_error_handler.py
tests/coco_tests/b09/__init__.py
tests/coco_tests/b09/test_b09.py
tests/coco_tests/b09/test_configs.py
tests/coco_tests/b09/test_visitors.py
tests/coco_tests/fixtures/__init__.py