Metadata-Version: 2.4
Name: coco-tools
Version: 0.20
Summary: TRS-80 Color Computer Tools
Author-email: Jamie Cho <jamieleecho@gmail.com>
License-Expression: GPL-2.0
Project-URL: Repository, https://github.com/jamieleecho/coco-tools
Project-URL: Issues, https://github.com/jamieleecho/coco-tools/issues
Keywords: coco,image,conversion,trs-80,tandy
Classifier: Development Status :: 3 - Alpha
Classifier: Intended Audience :: Developers
Classifier: Topic :: Software Development :: Build Tools
Classifier: Programming Language :: Python :: 3
Requires-Python: >=3.9.19
License-File: LICENSE
Requires-Dist: parsimonious>=0.10.0
Requires-Dist: Pillow>=7.0.0
Requires-Dist: pypng>=0.0.18
Requires-Dist: pydantic>=2.0.0
Requires-Dist: pydantic-yaml>=1.3.0
Dynamic: license-file
